easyplotter/__init__.py
easyplotter-1.0.1.dist-info/LICENSE
easyplotter-1.0.1.dist-info/METADATA
easyplotter-1.0.1.dist-info/WHEEL
easyplotter-1.0.1.dist-info/top_level.txt
easyplotter-1.0.1.dist-info/RECORD
